translator.py
EnToFa-1.4.2.dist-info/LICENSE
EnToFa-1.4.2.dist-info/METADATA
EnToFa-1.4.2.dist-info/WHEEL
EnToFa-1.4.2.dist-info/entry_points.txt
EnToFa-1.4.2.dist-info/top_level.txt
EnToFa-1.4.2.dist-info/RECORD
