Metadata-Version: 2.1
Name: EnToFa
Version: 1.4.2
License-File: LICENSE
Requires-Dist: requests
Requires-Dist: win10toast
